notify_me/__init__.py
notify_me/cli.py
notify_me/config.py
notify_me/notifier.py
notifyme_cli-1.0.1.dist-info/licenses/LICENSE
notifyme_cli-1.0.1.dist-info/METADATA
notifyme_cli-1.0.1.dist-info/WHEEL
notifyme_cli-1.0.1.dist-info/entry_points.txt
notifyme_cli-1.0.1.dist-info/top_level.txt
notifyme_cli-1.0.1.dist-info/RECORD
